LICENSE
MANIFEST.in
README.rst
setup.py
mezzanine_theme_moderna.egg-info/PKG-INFO
mezzanine_theme_moderna.egg-info/SOURCES.txt
mezzanine_theme_moderna.egg-info/dependency_links.txt
mezzanine_theme_moderna.egg-info/top_level.txt
moderna/__init__.py
moderna/static
moderna/templates
moderna/../moderna/static/css/animate.css
moderna/../moderna/static/css/bootstrap.min.css
moderna/../moderna/static/css/custom-fonts.css
moderna/../moderna/static/css/flexslider.css
moderna/../moderna/static/css/font-awesome.css
moderna/../moderna/static/css/mezzanine.css
moderna/../moderna/static/css/overwrite.css
moderna/../moderna/static/css/style.css
moderna/../moderna/static/css/fancybox/blank.gif
moderna/../moderna/static/css/fancybox/fancybox_loading.gif
moderna/../moderna/static/css/fancybox/fancybox_overlay.png
moderna/../moderna/static/css/fancybox/fancybox_sprite.png
moderna/../moderna/static/css/fancybox/jquery.fancybox.css
moderna/../moderna/static/fonts/FontAwesome.otf
moderna/../moderna/static/fonts/fontawesome-webfont.eot
moderna/../moderna/static/fonts/fontawesome-webfont.svg
moderna/../moderna/static/fonts/fontawesome-webfont.ttf
moderna/../moderna/static/fonts/fontawesome-webfont.woff
moderna/../moderna/static/fonts/customicon/Icons.eot
moderna/../moderna/static/fonts/customicon/Icons.svg
moderna/../moderna/static/fonts/customicon/Icons.ttf
moderna/../moderna/static/fonts/customicon/Icons.woff
moderna/../moderna/static/img/avatar.png
moderna/../moderna/static/img/bg_direction_nav.png
moderna/../moderna/static/img/glyphicons-halflings-white.png
moderna/../moderna/static/img/glyphicons-halflings.png
moderna/../moderna/static/img/nivo-bullets.png
moderna/../moderna/static/img/dummies/dummy-1.jpg
moderna/../moderna/static/img/dummies/blog/img1.jpg
moderna/../moderna/static/img/dummies/blog/img2.jpg
moderna/../moderna/static/img/dummies/blog/img3.jpg
moderna/../moderna/static/img/dummies/blog/65x65/thumb1.jpg
moderna/../moderna/static/img/dummies/blog/65x65/thumb2.jpg
moderna/../moderna/static/img/dummies/blog/65x65/thumb3.jpg
moderna/../moderna/static/img/slides/1.jpg
moderna/../moderna/static/img/slides/2.jpg
moderna/../moderna/static/img/slides/3.jpg
