Metadata-Version: 1.1
Name: mezzanine-theme-moderna
Version: 0.2
Summary: Mezzanine CMS theme: Moderna
Home-page: https://github.com/mxposed/mezzanine-theme-moderna
Author: Jay Bird
Author-email: a4blank@yahoo.com
License: MIT
Download-URL: https://github.com/mxposed/mezzanine-theme-moderna/archive/v0.2.tar.gz
Platform: UNKNOWN
